{"name":"Permutas SEP","tagline":"Ayuda a los profesores de México a encontrar su cambio de adscripción.","body":"### Permutas SEP\r\nPermutas SEP ayuda a los profesores de México a encontrar, de una manera mas ágil y rápida, sus cambios de adscripción.\r\n\r\n[![Descargar de Google Play](https://developer.android.com/images/brand/en_app_rgb_wo_45.png)](https://play.google.com/store/apps/details?id=com.permutassep)\r\n\r\n\r\n### ¿Cuál es la problemática?\r\nSeguramente todos tenemos a un familiar, amigo o conocido que es profesor de la SEP.\r\n\r\nBien, pues existen algunos maestros a quienes se les manda a laborar a un lugar muy lejos de su lugar de origen. Regularmente pasa esto con los maestros recién egresados de las Escuelas Normales, quienes en busca de una plaza dentro de la SEP, tienen que aceptar esta condición: trabajar dando clases lejos de casa.\r\n\r\nPara permitir a los profesores de México acercarse a su lugar de origen, la SEP emite cada ciclo escolar una convocatoria para que los profesores se inscriban solicitando el estado, municipio o localidad deseada. El problema con esta convocatoria es que, no siempre existen lugares disponibles para los profesores, lo que conlleva a esperar todo un ciclo escolar \r\n\r\n### ¿Cuál es la situación actual?\r\nLos maestros que trabajan lejos de su lugar de origen, han recurrido a diferentes medios para encontrar una permuta, que consiste en encontrar a un profesor en otra escuela de otra localidad, municipio o estado para realizar el intercambio de zona de trabajo, que se conoce como \"Cambio de adscripción\".\r\n\r\nLos medios a los que han recurrido los profesores son Blogs y grupos de Facebook, en donde cada uno de ellos publica su permuta deseada y espera a que otro mas lo contacte por ese medio.\r\n\r\nEste sistema adoptado tiene 2 problemas:\r\n\r\n- Es dificil encontrar una publicación que esté destinada a determinado determinado centro de trabajo en determinado lugar.\r\n- La información no está centralizada y los porfesores tienen que buscar entre blogs y diversos grupos de Facebook.\r\n- En la mayoría de los casos, es dificil encontrar una permuta uno a uno (1 - 1), y se tiene que recurrir a una triangulación.\r\n\r\nPor ejemplo:\r\n\r\n- Existe un profesor que labora en el estado de San Luis Potosí y quiere llegar al estado de Nuevo León.\r\n- De pronto, es contactado (por los medios mencionados anteriormente) por un profesor que labora en el estado de Veracruz que quiere llegar a San Luis Potosí.\r\n- Entonces, ambos se deben de dar a la tarea de buscar a un profesor que esté interesado en cambiar de zona de trabajo desde Nuevo León a Veracruz.\r\n\r\nAunque ahora son 2 profesores persiguiendo un fin común, este objetivo aveces no se logra y se pierda una valiosa oportunidad para que los profesores se acerquen sus lugares de origen o centros de trabajo deseados.\r\n\r\n### ¿Cuál es la solución propuesta?\r\nHemos creado una aplicación que permita a los profesores de México publicar y buscar permutas de una manera mas rápida.\r\nEsto ayudará a que los profesores lleguen a sus centros de trabajo deseados y desempeñen de una mejor manera su labor como profesores.\r\n\r\n### ¿Cuál es nuestra visión?\r\nComo todo proyecto, esta iniciativa se puede mejorar.\r\nAsí que, queremos agregar más y mejores funcionalidades a la aplicación, como son:\r\n\r\n- Chat entre profesores registrados\r\n- Ubicación de los centros de trabajo en Google Maps\r\n- Enviar sugerencias a los profesores acerca de los centros de trabajo mas cercanos a su lugar deseado.\r\n\r\n### ¿Quienes somos?\r\nEste es un proyecto hecho con :heart: por:\r\n- Cresencio Cruz [@krescruz](https://twitter.com/krescruz)\r\n- Jorge E. Hernández [@lalongooo](https://twitter.com/lalongooo)\r\n","google":"UA-62325816-1","note":"Don't delete this file! It's used internally to help with page regeneration."}